{
    "key": "group_64773b56507f3",
    "title": "FC - Rates",
    "fields": [
        {
            "key": "field_64773b5658d3e",
            "label": "Content",
            "name": "content",
            "aria-label": "",
            "type": "clone",
            "instructions": "",
            "required": 0,
            "conditional_logic": 0,
            "wrapper": {
                "width": "",
                "class": "",
                "id": ""
            },
            "clone": [
                "field_5a04301fabc52"
            ],
            "display": "seamless",
            "layout": "block",
            "prefix_label": 0,
            "prefix_name": 0,
            "acfe_seamless_style": 0,
            "acfe_clone_modal": 0,
            "acfe_clone_modal_close": 0,
            "acfe_clone_modal_button": "",
            "acfe_clone_modal_size": "large"
        },
        {
            "key": "field_64773bfdc6b1c",
            "label": "Heading",
            "name": "heading",
            "aria-label": "",
            "type": "text",
            "instructions": "",
            "required": 0,
            "conditional_logic": 0,
            "wrapper": {
                "width": "50",
                "class": "",
                "id": ""
            },
            "acfe_save_meta": 0,
            "default_value": "",
            "maxlength": "",
            "placeholder": "",
            "prepend": "",
            "append": ""
        },
        {
            "key": "field_64773c11c6b1d",
            "label": "Caption",
            "name": "caption",
            "aria-label": "",
            "type": "text",
            "instructions": "",
            "required": 0,
            "conditional_logic": 0,
            "wrapper": {
                "width": "50",
                "class": "",
                "id": ""
            },
            "acfe_save_meta": 0,
            "default_value": "",
            "maxlength": "",
            "placeholder": "",
            "prepend": "",
            "append": ""
        },
        {
            "key": "field_64808948a0a8a",
            "label": "Stats Type",
            "name": "stats_type",
            "aria-label": "",
            "type": "button_group",
            "instructions": "",
            "required": 0,
            "conditional_logic": 0,
            "wrapper": {
                "width": "",
                "class": "",
                "id": ""
            },
            "acfe_save_meta": 0,
            "choices": {
                "client": "Client",
                "custom": "Custom"
            },
            "default_value": "client",
            "return_format": "value",
            "allow_null": 0,
            "layout": "horizontal"
        },
        {
            "key": "field_64773c2b9d4c2",
            "label": "Stats",
            "name": "stats",
            "aria-label": "",
            "type": "repeater",
            "instructions": "",
            "required": 0,
            "conditional_logic": [
                [
                    {
                        "field": "field_64808948a0a8a",
                        "operator": "==",
                        "value": "custom"
                    }
                ]
            ],
            "wrapper": {
                "width": "",
                "class": "",
                "id": ""
            },
            "acfe_save_meta": 0,
            "acfe_repeater_stylised_button": 0,
            "layout": "table",
            "pagination": 0,
            "min": 0,
            "max": 0,
            "collapsed": "",
            "button_label": "Add Row",
            "rows_per_page": 20,
            "sub_fields": [
                {
                    "key": "field_64773c369d4c3",
                    "label": "Label",
                    "name": "label",
                    "aria-label": "",
                    "type": "text",
                    "instructions": "",
                    "required": 0,
                    "conditional_logic": 0,
                    "wrapper": {
                        "width": "33.3333333",
                        "class": "",
                        "id": ""
                    },
                    "acfe_save_meta": 0,
                    "default_value": "",
                    "maxlength": "",
                    "placeholder": "",
                    "prepend": "",
                    "append": "",
                    "parent_repeater": "field_64773c2b9d4c2"
                },
                {
                    "key": "field_64773c489d4c4",
                    "label": "Value",
                    "name": "value",
                    "aria-label": "",
                    "type": "text",
                    "instructions": "",
                    "required": 0,
                    "conditional_logic": 0,
                    "wrapper": {
                        "width": "33.3333333",
                        "class": "",
                        "id": ""
                    },
                    "acfe_save_meta": 0,
                    "default_value": "",
                    "maxlength": "",
                    "placeholder": "",
                    "prepend": "",
                    "append": "",
                    "parent_repeater": "field_64773c2b9d4c2"
                },
                {
                    "key": "field_64773c619d4c5",
                    "label": "Symbol",
                    "name": "symbol",
                    "aria-label": "",
                    "type": "text",
                    "instructions": "",
                    "required": 0,
                    "conditional_logic": 0,
                    "wrapper": {
                        "width": "33.3333333",
                        "class": "",
                        "id": ""
                    },
                    "acfe_save_meta": 0,
                    "default_value": "",
                    "maxlength": "",
                    "placeholder": "",
                    "prepend": "",
                    "append": "",
                    "parent_repeater": "field_64773c2b9d4c2"
                }
            ]
        },
        {
            "key": "field_648089be206df",
            "label": "Client",
            "name": "client",
            "aria-label": "",
            "type": "post_object",
            "instructions": "",
            "required": 0,
            "conditional_logic": [
                [
                    {
                        "field": "field_64808948a0a8a",
                        "operator": "==",
                        "value": "client"
                    }
                ]
            ],
            "wrapper": {
                "width": "",
                "class": "",
                "id": ""
            },
            "acfe_save_meta": 0,
            "post_type": [
                "rate"
            ],
            "post_status": "",
            "taxonomy": "",
            "return_format": "id",
            "multiple": 0,
            "save_custom": 0,
            "save_post_status": "publish",
            "acfe_bidirectional": {
                "acfe_bidirectional_enabled": "0"
            },
            "allow_null": 0,
            "ui": 1,
            "save_post_type": ""
        },
        {
            "key": "field_6480830e1fb2f",
            "label": "Small Print",
            "name": "small_print",
            "aria-label": "",
            "type": "textarea",
            "instructions": "",
            "required": 0,
            "conditional_logic": 0,
            "wrapper": {
                "width": "",
                "class": "",
                "id": ""
            },
            "acfe_save_meta": 0,
            "default_value": "Rates are correct on the Insignis Cash Platform as of %rates-date%. Rates are subject to a minimum and maximum deposit size. Availability of product will vary depending on the client type.",
            "acfe_textarea_code": 0,
            "maxlength": "",
            "rows": 3,
            "placeholder": "",
            "new_lines": ""
        },
        {
            "key": "field_64773b5658e4d",
            "label": "Options",
            "name": "options",
            "aria-label": "",
            "type": "clone",
            "instructions": "",
            "required": 0,
            "conditional_logic": 0,
            "wrapper": {
                "width": "",
                "class": "",
                "id": ""
            },
            "clone": [
                "field_5a042f1f520f3"
            ],
            "display": "seamless",
            "layout": "block",
            "prefix_label": 0,
            "prefix_name": 0,
            "acfe_seamless_style": 0,
            "acfe_clone_modal": 0,
            "acfe_clone_modal_close": 0,
            "acfe_clone_modal_button": "",
            "acfe_clone_modal_size": "large"
        },
        {
            "key": "field_64773b5658ea9",
            "label": "Options",
            "name": "options",
            "aria-label": "",
            "type": "clone",
            "instructions": "",
            "required": 0,
            "conditional_logic": 0,
            "wrapper": {
                "width": "",
                "class": "",
                "id": ""
            },
            "clone": [
                "field_5acf56bd8248f"
            ],
            "display": "seamless",
            "layout": "block",
            "prefix_label": 0,
            "prefix_name": 0,
            "acfe_seamless_style": 0,
            "acfe_clone_modal": 0,
            "acfe_clone_modal_close": 0,
            "acfe_clone_modal_button": "",
            "acfe_clone_modal_size": "large"
        },
        {
            "key": "field_64773b5658eea",
            "label": "Styles",
            "name": "styles",
            "aria-label": "",
            "type": "clone",
            "instructions": "",
            "required": 0,
            "conditional_logic": 0,
            "wrapper": {
                "width": "",
                "class": "",
                "id": ""
            },
            "clone": [
                "field_5a043e37b407f"
            ],
            "display": "seamless",
            "layout": "block",
            "prefix_label": 0,
            "prefix_name": 0,
            "acfe_seamless_style": 0,
            "acfe_clone_modal": 0,
            "acfe_clone_modal_close": 0,
            "acfe_clone_modal_button": "",
            "acfe_clone_modal_size": "large"
        },
        {
            "key": "field_64773b5658f26",
            "label": "Styles",
            "name": "fc_styles",
            "aria-label": "",
            "type": "clone",
            "instructions": "",
            "required": 0,
            "conditional_logic": 0,
            "wrapper": {
                "width": "",
                "class": "",
                "id": ""
            },
            "clone": [
                "field_5a043e21b407e"
            ],
            "display": "seamless",
            "layout": "block",
            "prefix_label": 0,
            "prefix_name": 0,
            "acfe_seamless_style": 0,
            "acfe_clone_modal": 0,
            "acfe_clone_modal_close": 0,
            "acfe_clone_modal_button": "",
            "acfe_clone_modal_size": "large"
        }
    ],
    "location": [
        [
            {
                "param": "post_type",
                "operator": "==",
                "value": "post"
            }
        ]
    ],
    "menu_order": 0,
    "position": "normal",
    "style": "default",
    "label_placement": "left",
    "instruction_placement": "label",
    "hide_on_screen": "",
    "active": false,
    "description": "",
    "show_in_rest": 0,
    "acfe_display_title": "",
    "acfe_autosync": [
        "json"
    ],
    "acfe_form": 0,
    "acfe_meta": "",
    "acfe_note": "",
    "modified": 1686145513
}